Metadata-Version: 1.2
Name: fever-allennlp-reader
Version: 1.6.38
Summary: Fact Extraction and VERification dataset reader for AllenNLP
Home-page: https://jamesthorne.co.uk
Author: James Thorne
Author-email: james@jamesthorne.co.uk
License: Type license() to see the full license text
Platform: UNKNOWN
Requires-Python: >=3.6
